{
    "version": "0.0.17",
    "description": "dwm-win32 is a port of the well known X11 window manager dwm to Microsoft Windows.",
    "homepage": "https://github.com/prabirshrestha/dwm-win32",
    "license": "MIT/X",
    "architecture": {
        "64bit": {
            "url": "https://github.com/prabirshrestha/dwm-win32/releases/download/v0.0.17/dwm-win32.exe"
        }
    },
    "bin": "dwm.exe",
    "checkver": {
"github": "https://github.com/prabirshrestha/dwm-win32"
    },
    "autoupdate": {
        "architecture": {
            "64bit": {
                "url": "https://github.com/prabirshrestha/dwm-win32/releases/download/$version/dwm-win32.exe"
            }
        },
              "hash": {
            "url": "$baseurl/SHA2-512SUMS"
        }
    }
}